dynamicscope.py
dynamicscope-1.0.4.dist-info/LICENSE
dynamicscope-1.0.4.dist-info/METADATA
dynamicscope-1.0.4.dist-info/WHEEL
dynamicscope-1.0.4.dist-info/top_level.txt
dynamicscope-1.0.4.dist-info/RECORD
