Metadata-Version: 2.1
Name: dynamicscope
Version: 1.0.4
Summary: Emulate dynamic scope in Python.
Home-page: https://github.com/mentalisttraceur/python-dynamicscope
Author: Alexander Kozhevnikov
Author-email: mentalisttraceur@gmail.com
License: 0BSD
Platform: UNKNOWN
Classifier: Development Status :: 5 - Production/Stable
Classifier: Programming Language :: Python :: 3
Classifier: Programming Language :: Python :: 2
Classifier: Operating System :: OS Independent
License-File: LICENSE
